texto/__init__.py
texto/algorithms/concordancier.py
texto/algorithms/dispersion.py
texto/algorithms/ramer.py
texto/cache/lab1.pkl
texto/cache/lab1s.pkl
texto/cache/lab2.pkl
texto/cache/lab2s.pkl
texto/cache/lab3.pkl
texto/cache/lab3s.pkl
texto/entry.py
texto/utils/token.py
texto-0.1.4.dist-info/entry_points.txt
texto-0.1.4.dist-info/WHEEL
texto-0.1.4.dist-info/METADATA
texto-0.1.4.dist-info/RECORD
