Metadata-Version: 2.1
Name: texto
Version: 0.1.4
Summary: Projet de textométrie.
Author: Jérémy DEMANGE
Author-email: jeremy@scrapfast.io
Requires-Python: >=3.6,<4.0
Classifier: Programming Language :: Python :: 3
Classifier: Programming Language :: Python :: 3.6
Classifier: Programming Language :: Python :: 3.7
Classifier: Programming Language :: Python :: 3.8
Classifier: Programming Language :: Python :: 3.9
Requires-Dist: click (>=7.1.2,<8.0.0)
Requires-Dist: gensim (==4.0.0b0)
Requires-Dist: matplotlib (==3.3.4)
Requires-Dist: nltk (==3.5)
Requires-Dist: spacy (==3.0.3)
